README.md
setup.py
app/__init__.py
app/analysis/__init__.py
app/analysis/threat_detector.py
app/analysis/traffic_analyzer.py
app/capture/__init__.py
app/capture/packet_capture.py
app/capture/protocol_analyzer.py
app/dashboard/__init__.py
app/dashboard/routes.py
app/models/__init__.py
app/models/database.py
app/models/packet_model.py
cli/__init__.py
cli/main.py
config/__init__.py
config/settings.py
smart_packet_sniffer.egg-info/PKG-INFO
smart_packet_sniffer.egg-info/SOURCES.txt
smart_packet_sniffer.egg-info/dependency_links.txt
smart_packet_sniffer.egg-info/entry_points.txt
smart_packet_sniffer.egg-info/requires.txt
smart_packet_sniffer.egg-info/top_level.txt